Pipfile
Pipfile.lock
README.md
setup.py
consoleProgressbarPanel/__init__.py
consoleProgressbarPanel/component.py
consoleProgressbarPanel/consoleProgressbarPanel.py
consoleProgressbarPanel.egg-info/PKG-INFO
consoleProgressbarPanel.egg-info/SOURCES.txt
consoleProgressbarPanel.egg-info/dependency_links.txt
consoleProgressbarPanel.egg-info/top_level.txt
dist/consoleProgressbarPanel-0.1.7.tar.gz